{"description": "", "tags": [], "size": {"height": 768, "width": 768}, "objects": [{"description": "", "bitmap": null, "tags": [], "classTitle": "driveways_line", "points": {"exterior": [[265, 185], [279, 127]], "interior": []}}, {"description": "", "bitmap": null, "tags": [], "classTitle": "driveways_line", "points": {"exterior": [[283, 99], [291, 57]], "interior": []}}, {"description": "", "bitmap": null, "tags": [], "classTitle": "driveways_line", "points": {"exterior": [[259, 218], [251, 262]], "interior": []}}, {"description": "", "bitmap": null, "tags": [], "classTitle": "driveways_line", "points": {"exterior": [[373, 678], [364, 736]], "interior": []}}, {"description": "", "bitmap": null, "tags": [], "classTitle": "driveways_line", "points": {"exterior": [[394, 567], [416, 469]], "interior": []}}, {"description": "", "bitmap": null, "tags": [], "classTitle": "driveways_line", "points": {"exterior": [[440, 342], [450, 296]], "interior": []}}, {"description": "", "bitmap": null, "tags": [], "classTitle": "driveways_line", "points": {"exterior": [[496, 58], [506, 3]], "interior": []}}]}