{"description": "", "tags": [], "size": {"height": 768, "width": 768}, "objects": [{"description": "", "bitmap": null, "tags": [], "classTitle": "Poly", "points": {"exterior": [[6, 1], [86, 2], [88, 17], [3, 23]], "interior": []}}, {"description": "", "bitmap": null, "tags": [], "classTitle": "Poly", "points": {"exterior": [[5, 101], [80, 97], [90, 164], [8, 168]], "interior": []}}, {"description": "", "bitmap": null, "tags": [], "classTitle": "Poly", "points": {"exterior": [[204, 6], [208, 137], [282, 137], [275, 6]], "interior": []}}]}