{"description": "", "tags": [], "size": {"height": 768, "width": 768}, "objects": [{"description": "", "bitmap": null, "tags": [], "classTitle": "Poly", "points": {"exterior": [[228, 141], [278, 207], [545, 0], [397, 0]], "interior": []}}, {"description": "", "bitmap": null, "tags": [], "classTitle": "Poly", "points": {"exterior": [[179, 435], [250, 501], [768, 27], [683, 0]], "interior": []}}, {"description": "", "bitmap": null, "tags": [], "classTitle": "Poly", "points": {"exterior": [[241, 501], [299, 567], [768, 140], [768, 22]], "interior": []}}, {"description": "", "bitmap": null, "tags": [], "classTitle": "Poly", "points": {"exterior": [[768, 290], [320, 682], [384, 746], [768, 404]], "interior": []}}, {"description": "", "bitmap": null, "tags": [], "classTitle": "Poly", "points": {"exterior": [[0, 383], [0, 504], [234, 760], [299, 714]], "interior": []}}, {"description": "", "bitmap": null, "tags": [], "classTitle": "Poly", "points": {"exterior": [[112, 290], [187, 309], [250, 0], [161, 0]], "interior": []}}, {"description": "", "bitmap": null, "tags": [], "classTitle": "Poly", "points": {"exterior": [[63, 0], [3, 0], [0, 160], [0, 336]], "interior": []}}]}