{"description": "", "tags": [], "size": {"height": 256, "width": 256}, "objects": [{"description": "", "bitmap": null, "tags": [], "classTitle": "Driveway", "points": {"exterior": [[162, 26], [167, 83]], "interior": []}}, {"description": "", "bitmap": null, "tags": [], "classTitle": "edge_of_road", "points": {"exterior": [[166, 89], [175, 254]], "interior": []}}, {"description": "", "bitmap": null, "tags": [], "classTitle": "edge_of_road", "points": {"exterior": [[60, 113], [66, 255]], "interior": []}}, {"description": "", "bitmap": null, "tags": [], "classTitle": "edge_of_road", "points": {"exterior": [[23, 94], [2, 98]], "interior": []}}, {"description": "", "bitmap": null, "tags": [], "classTitle": "edge_of_road", "points": {"exterior": [[162, 24], [162, 2]], "interior": []}}, {"description": "", "bitmap": null, "tags": [], "classTitle": "Driveway", "points": {"exterior": [[26, 93], [44, 98]], "interior": []}}, {"description": "", "bitmap": null, "tags": [], "classTitle": "Driveway", "points": {"exterior": [[46, 99], [58, 112]], "interior": []}}]}